protiler_mut/__init__.py
protiler_mut/cli.py
protiler_mut/cluster.py
protiler_mut/fetchProteinDatabase.py
protiler_mut/ppi_mapping.py
protiler_mut/threeD_rra.py
protiler_mut-0.1.0.dist-info/LICENSE
protiler_mut-0.1.0.dist-info/METADATA
protiler_mut-0.1.0.dist-info/WHEEL
protiler_mut-0.1.0.dist-info/entry_points.txt
protiler_mut-0.1.0.dist-info/top_level.txt
protiler_mut-0.1.0.dist-info/RECORD
