Metadata-Version: 2.1
Name: protiler-mut
Version: 0.1.0
Summary: Pipeline for comprehensive analysis of tiling mutagenesis data
Author-email: Wei He <hwkobe.1027@gmail.com>
License: GUN
Project-URL: Homepage, https://github.com/MDhewei/ProTiler-Mut
Requires-Python: >=3.7
License-File: LICENSE
